{
  "subjects": [
    {
      "id": 1,
      "number": "1",
      "text": "банктер"
    },
    {
      "id": 2,
      "number": "2",
      "text": "Қазақстан Республикасының резидент емес банктерінің филиалдары"
    },
    {
      "id": 3,
      "number": "3",
      "text": "айырбастау пункттері"
    },
    {
      "id": 4,
      "number": "4",
      "text": "биржалар"
    },
    {
      "id": 5,
      "number": "5",
      "text": "сақтандыру (қайта сақтандыру) ұйымдары"
    },
    {
      "id": 6,
      "number": "6",
      "text": "сақтандыру брокерлері"
    },
    {
      "id": 7,
      "number": "7",
      "text": "өзара сақтандыру қоғамдары"
    },
    {
      "id": 8,
      "number": "8",
      "text": "Қазақстан Республикасының резидент емес банктерінің филиалдары"
    },
    {
      "id": 9,
      "number": "9",
      "text": "Қазақстан Республикасының резидент емес-сақтандыру брокерлерінің филиалдары"
    },
    {
      "id": 10,
      "number": "10",
      "text": "Бірыңғай жинақтаушы зейнетақы қоры және ерікті жинақтаушы зейнетақы қорлары"
    },
    {
      "id": 11,
      "number": "11",
      "text": "бағалы қағаздар нарығының кәсіби қатысушылары"
    },
    {
      "id": 12,
      "number": "12",
      "text": "Орталық депозитарий"
    },
    {
      "id": 13,
      "number": "13",
      "text": "ақшамен және (немесе) өзге мүлікпен нотариаттық әрекеттерді жүзеге асыратын нотариустар"
    },
    {
      "id": 14,
      "number": "14",
      "text": "адвокаттар"
    },
    {
      "id": 15,
      "number": "15",
      "text": "заң кеңесшілері"
    },
    {
      "id": 16,
      "number": "16",
      "text": "басқа тәуелсіз Заң мамандары"
    },
    {
      "id": 17,
      "number": "17",
      "text": "бухгалтерлік ұйымдар"
    },
    {
      "id": 18,
      "number": "18",
      "text": "бухгалтерлік есеп саласында кәсіпкерлік қызметті жүзеге асыратын кәсіби бухгалтерлер"
    },
    {
      "id": 19,
      "number": "19",
      "text": "аудиторлық ұйымдар"
    },
    {
      "id": 20,
      "number": "20",
      "text": "ойын бизнесін ұйымдастырушылар"
    },
    {
      "id": 21,
      "number": "21",
      "text": "лотерея ұйымдастырушылары"
    },
    {
      "id": 22,
      "number": "22",
      "text": "ақша аудару қызметтерін көрсететін пошта операторлары"
    },
    {
      "id": 23,
      "number": "23",
      "text": "микроқаржы ұйымдары"
    },
    {
      "id": 24,
      "number": "24",
      "text": "ломбардтар"
    },
    {
      "id": 25,
      "number": "25",
      "text": "кредиттік серіктестіктер"
    },
    {
      "id": 26,
      "number": "26",
      "text": "төлем ұйымдары"
    },
    {
      "id": 27,
      "number": "27",
      "text": "Лицензиясыз лизинг беруші ретінде лизингтік қызметті жүзеге асыратын ЖК және ЗТ"
    },
    {
      "id": 28,
      "number": "28",
      "text": "Бағалы металдармен және асыл тастармен, олардан жасалған зергерлік бұйымдармен операцияларды жүзеге асыратын ЖК және ЗТ"
    },
    {
      "id": 29,
      "number": "29",
      "text": "Жылжымайтын мүлікті сатып алу-сату мәмілелерін жүзеге асыру кезінде делдалдық қызмет көрсететін ЖК және ЗТ"
    },
    {
      "id": 30,
      "number": "30",
      "text": "әлеуметтік медициналық сақтандыру қоры"
    },
    {
      "id": 31,
      "number": "31",
      "text": "АХҚО қатысушылары"
    },
    {
      "id": 32,
      "number": "32",
      "text": "цифрлық активтерді шығару, олармен сауда-саттықты ұйымдастыру, сондай-ақ цифрлық активтерді ақшаға, құндылықтарға және өзге де мүлікке айырбастау жөніндегі қызметтерді ұсыну жөніндегі қызметті жүзеге асыратын тұлғалар"
    }
  ]
}
